fastcdr/_dummy.cpython-311-x86_64-linux-gnu.so
ros_fastcdr-2.3.3.data/data/include/fastcdr/Cdr.h
ros_fastcdr-2.3.3.data/data/include/fastcdr/CdrEncoding.hpp
ros_fastcdr-2.3.3.data/data/include/fastcdr/CdrSizeCalculator.hpp
ros_fastcdr-2.3.3.data/data/include/fastcdr/FastBuffer.h
ros_fastcdr-2.3.3.data/data/include/fastcdr/FastCdr.h
ros_fastcdr-2.3.3.data/data/include/fastcdr/config.h
ros_fastcdr-2.3.3.data/data/include/fastcdr/eProsima_auto_link.h
ros_fastcdr-2.3.3.data/data/include/fastcdr/fastcdr_dll.h
ros_fastcdr-2.3.3.data/data/include/fastcdr/cdr/fixed_size_string.hpp
ros_fastcdr-2.3.3.data/data/include/fastcdr/config/doxygen_modules.h
ros_fastcdr-2.3.3.data/data/include/fastcdr/detail/container_recursive_inspector.hpp
ros_fastcdr-2.3.3.data/data/include/fastcdr/exceptions/BadOptionalAccessException.hpp
ros_fastcdr-2.3.3.data/data/include/fastcdr/exceptions/BadParamException.h
ros_fastcdr-2.3.3.data/data/include/fastcdr/exceptions/Exception.h
ros_fastcdr-2.3.3.data/data/include/fastcdr/exceptions/LockedExternalAccessException.hpp
ros_fastcdr-2.3.3.data/data/include/fastcdr/exceptions/NotEnoughMemoryException.h
ros_fastcdr-2.3.3.data/data/include/fastcdr/xcdr/MemberId.hpp
ros_fastcdr-2.3.3.data/data/include/fastcdr/xcdr/external.hpp
ros_fastcdr-2.3.3.data/data/include/fastcdr/xcdr/optional.hpp
ros_fastcdr-2.3.3.data/data/include/fastcdr/xcdr/detail/optional.hpp
ros_fastcdr-2.3.3.data/data/lib/libfastcdr.so
ros_fastcdr-2.3.3.data/data/lib/libfastcdr.so.2
ros_fastcdr-2.3.3.data/data/lib/libfastcdr.so.2.3.3
ros_fastcdr-2.3.3.data/data/lib/cmake/fastcdr/fastcdr-config-version.cmake
ros_fastcdr-2.3.3.data/data/lib/cmake/fastcdr/fastcdr-config.cmake
ros_fastcdr-2.3.3.data/data/lib/cmake/fastcdr/fastcdr-shared-targets-release.cmake
ros_fastcdr-2.3.3.data/data/lib/cmake/fastcdr/fastcdr-shared-targets.cmake
ros_fastcdr-2.3.3.data/data/share/fastcdr/LICENSE
ros_fastcdr-2.3.3.dist-info/METADATA
ros_fastcdr-2.3.3.dist-info/WHEEL
ros_fastcdr-2.3.3.dist-info/top_level.txt
ros_fastcdr-2.3.3.dist-info/RECORD
ros_fastcdr-2.3.3.dist-info/licenses/LICENSE
