Metadata-Version: 2.4
Name: ros-fastcdr
Version: 2.3.3
Summary: fastcdr is a ROS package providing Python bindings for eProsima Fast CDR, a library for efficient data serialization and deserialization.
License-File: LICENSE
Dynamic: description
Dynamic: description-content-type
Dynamic: license-file
Dynamic: summary
